quantastica_qiskit_toaster-0.9.30-py3.8-nspkg.pth
quantastica/qiskit_toaster/ToasterBackend.py
quantastica/qiskit_toaster/ToasterCliInterface.py
quantastica/qiskit_toaster/ToasterHttpInterface.py
quantastica/qiskit_toaster/ToasterJob.py
quantastica/qiskit_toaster/__init__.py
tests/__init__.py
tests/common.py
tests/test_benchmark.py
tests/test_qft25.py
tests/test_toasterbackend.py
tests/manual/test_qaoa.py
quantastica_qiskit_toaster-0.9.30.dist-info/LICENSE
quantastica_qiskit_toaster-0.9.30.dist-info/METADATA
quantastica_qiskit_toaster-0.9.30.dist-info/WHEEL
quantastica_qiskit_toaster-0.9.30.dist-info/namespace_packages.txt
quantastica_qiskit_toaster-0.9.30.dist-info/top_level.txt
quantastica_qiskit_toaster-0.9.30.dist-info/RECORD
