Metadata-Version: 2.1
Name: quantastica-qiskit-toaster
Version: 0.9.30
Summary: Qubit Toaster backend for Qiskit: run Qiskit code on Quantastica "Qubit Toaster" simulator
Home-page: https://github.com/quantastica/qiskit-toaster
Author: Quantastica
Author-email: support@quantastica.com
License: Apache License 2.0
Platform: UNKNOWN
Classifier: Development Status :: 4 - Beta
Classifier: License :: OSI Approved :: Apache Software License
Classifier: Programming Language :: Python :: 3
Classifier: Intended Audience :: Science/Research
Requires-Dist: qiskit-terra
Requires-Dist: numpy
Requires-Dist: quantastica-qconvert (>=0.9.20)
